{
  "n_sequences": 50,
  "gesture_types": [
    "grab",
    "reach",
    "point",
    "grab",
    "handover",
    "grab",
    "point",
    "point",
    "reach",
    "point",
    "grab",
    "grab",
    "reach",
    "reach",
    "handover",
    "grab",
    "point",
    "grab",
    "grab",
    "grab",
    "reach",
    "reach",
    "reach",
    "wave",
    "grab",
    "handover",
    "reach",
    "grab",
    "wave",
    "reach",
    "grab",
    "reach",
    "grab",
    "wave",
    "reach",
    "wave",
    "point",
    "handover",
    "grab",
    "grab",
    "grab",
    "wave",
    "handover",
    "grab",
    "point",
    "reach",
    "point",
    "reach",
    "point",
    "reach"
  ],
  "avg_duration": 1.87,
  "workspace_bounds": [
    -1.0,
    1.0,
    -1.0,
    1.0,
    0.0,
    2.0
  ],
  "sampling_frequency": 30.0
}